simple_table_dima203/__init__.py
simple_table_dima203/style.py
simple_table_dima203/table.py
simple_table_dima203-0.0.6.dist-info/licenses/LICENSE
simple_table_dima203-0.0.6.dist-info/METADATA
simple_table_dima203-0.0.6.dist-info/WHEEL
simple_table_dima203-0.0.6.dist-info/top_level.txt
simple_table_dima203-0.0.6.dist-info/RECORD
