Metadata-Version: 2.4
Name: simple_table_dima203
Version: 0.0.6
Summary: Simple package for fast work with tables
Author-email: dima203 <gg3752901@gmail.com>
License-Expression: MIT
Project-URL: Homepage, https://github.com/dima203/SimpleTable
Project-URL: Issues, https://github.com/dima203/SimpleTable/issues
Classifier: Programming Language :: Python :: 3
Classifier: Operating System :: OS Independent
Requires-Python: >=3.6
License-File: LICENSE
Dynamic: license-file
